{
  "date": "2025-02-04",
  "season": "2024-25",
  "period": null,
  "teams": [
    {
      "franchise": "Matt's mid tier perpetual projects",
      "name": "Matt's mid tier perpetual projects",
      "dayPts": 6,
      "projPts": 6,
      "gp": 10
    },
    {
      "franchise": "Jason's Gaucho Chudpumpers",
      "name": "Jason's Gaucho Chudpumpers",
      "dayPts": 11,
      "projPts": 11,
      "gp": 10
    },
    {
      "franchise": "Richie's Meatspinners",
      "name": "Richie's Meatspinners",
      "dayPts": 9,
      "projPts": 9,
      "gp": 12
    },
    {
      "franchise": "Brian's.Endless.Win ter.S12E01.720p.mp4",
      "name": "Brian's.Endless.Win ter.S12E01.720p.mp4",
      "dayPts": 6,
      "projPts": 6,
      "gp": 14
    },
    {
      "franchise": "Graeme's Downtown Demons",
      "name": "Graeme's Downtown Demons",
      "dayPts": 10,
      "projPts": 10,
      "gp": 11
    },
    {
      "franchise": "Cmack's PWN",
      "name": "Cmack's PWN",
      "dayPts": 10,
      "projPts": 10,
      "gp": 13
    }
  ]
}