{
  "date": "2021-02-05",
  "season": "2020-21",
  "period": null,
  "teams": [
    {
      "franchise": "Cmack's PWN",
      "name": "Cmack's PWN",
      "dayPts": 3,
      "projPts": 3,
      "gp": 2
    },
    {
      "franchise": "Jason's Gaucho Nation",
      "name": "Jason's Gaucho Nation",
      "dayPts": 3,
      "projPts": 3,
      "gp": 1
    },
    {
      "franchise": "Richie's Meatspinners",
      "name": "Richie's Meatspinners",
      "dayPts": 0,
      "projPts": 0,
      "gp": 1
    },
    {
      "franchise": "Matt's Ice Bandits",
      "name": "Matt's Ice Bandits",
      "dayPts": 0,
      "projPts": 0,
      "gp": 2
    },
    {
      "franchise": "Brian's Human Garbage",
      "name": "Brian's Human Garbage",
      "dayPts": 1,
      "projPts": 1,
      "gp": 3
    },
    {
      "franchise": "Graeme's Downtown Demons",
      "name": "Graeme's Downtown Demons",
      "dayPts": 2,
      "projPts": 2,
      "gp": 1
    }
  ]
}