{
  "date": "2018-10-04",
  "season": "2018-19",
  "period": null,
  "teams": [
    {
      "franchise": "Cmack's PWN",
      "name": "Cmack's PWN",
      "dayPts": 12,
      "projPts": 12,
      "gp": 11
    },
    {
      "franchise": "Brian's Glue Factory",
      "name": "Brian's Glue Factory",
      "dayPts": 6,
      "projPts": 6,
      "gp": 7
    },
    {
      "franchise": "Jason's Gaucho Nation",
      "name": "Jason's Gaucho Nation",
      "dayPts": 6,
      "projPts": 6,
      "gp": 10
    },
    {
      "franchise": "Graeme's Downtown Demons",
      "name": "Graeme's Downtown Demons",
      "dayPts": 13,
      "projPts": 13,
      "gp": 11
    },
    {
      "franchise": "Matt's Ice Bandits",
      "name": "Matt's Ice Bandits",
      "dayPts": 11,
      "projPts": 11,
      "gp": 11
    },
    {
      "franchise": "Richie's Meatspinners",
      "name": "Richie's Meatspinners",
      "dayPts": 5,
      "projPts": 5,
      "gp": 8
    }
  ]
}