{
  "date": "2015-12-27",
  "season": "2015-16",
  "period": null,
  "teams": [
    {
      "franchise": "CMack's PWN",
      "name": "CMack's PWN",
      "dayPts": 6,
      "projPts": 6,
      "gp": 4
    },
    {
      "franchise": "Jason's Gaucho Nation",
      "name": "Jason's Gaucho Nation",
      "dayPts": 11,
      "projPts": 11,
      "gp": 2
    },
    {
      "franchise": "Brian's Boitanos",
      "name": "Brian's Boitanos",
      "dayPts": 3,
      "projPts": 3,
      "gp": 1
    },
    {
      "franchise": "Matt's Cascadia Crew",
      "name": "Matt's Cascadia Crew",
      "dayPts": 7,
      "projPts": 7,
      "gp": 4
    },
    {
      "franchise": "Graeme's Downtown Demons",
      "name": "Graeme's Downtown Demons",
      "dayPts": 9,
      "projPts": 9,
      "gp": 0
    }
  ]
}