{
  "date": "2024-02-12",
  "season": "2023-24",
  "period": null,
  "teams": [
    {
      "franchise": "Cmack's PWN",
      "name": "Cmack's PWN",
      "dayPts": 1,
      "projPts": 1,
      "gp": 3
    },
    {
      "franchise": "Richie's Meatspinners",
      "name": "Richie's Meatspinners",
      "dayPts": 5,
      "projPts": 5,
      "gp": 4
    },
    {
      "franchise": "Jason's Gaucho Nation",
      "name": "Jason's Gaucho Nation",
      "dayPts": 2,
      "projPts": 2,
      "gp": 3
    },
    {
      "franchise": "Graeme's Downtown Demons",
      "name": "Graeme's Downtown Demons",
      "dayPts": 1,
      "projPts": 1,
      "gp": 1
    },
    {
      "franchise": "Brian's Future Conshiterations",
      "name": "Brian's Future Conshiterations",
      "dayPts": 5,
      "projPts": 5,
      "gp": 3
    },
    {
      "franchise": "Matt's mid tier perpetual projects",
      "name": "Matt's mid tier perpetual projects",
      "dayPts": 2,
      "projPts": 2,
      "gp": 1
    }
  ]
}