{
  "date": "2018-02-09",
  "season": "2017-18",
  "period": null,
  "teams": [
    {
      "franchise": "Cmack's PWN",
      "name": "Cmack's PWN",
      "dayPts": 9,
      "projPts": 9,
      "gp": 5
    },
    {
      "franchise": "Graeme's Downtown Demons",
      "name": "Graeme's Downtown Demons",
      "dayPts": 2,
      "projPts": 2,
      "gp": 2
    },
    {
      "franchise": "Jason's Gaucho Nation",
      "name": "Jason's Gaucho Nation",
      "dayPts": 10,
      "projPts": 10,
      "gp": 3
    },
    {
      "franchise": "Matt's Ice Bandits",
      "name": "Matt's Ice Bandits",
      "dayPts": 10,
      "projPts": 10,
      "gp": 1
    },
    {
      "franchise": "Brian's Glue Factory",
      "name": "Brian's Glue Factory",
      "dayPts": 5,
      "projPts": 5,
      "gp": 0
    },
    {
      "franchise": "Richie's Meatspinners",
      "name": "Richie's Meatspinners",
      "dayPts": 4,
      "projPts": 4,
      "gp": 2
    }
  ]
}